tinyml4all/__init__.py
tinyml4all/audio/Album.py
tinyml4all/audio/AzureTTS.py
tinyml4all/audio/WAV.py
tinyml4all/audio/__init__.py
tinyml4all/audio/capture.py
tinyml4all/audio/support.py
tinyml4all/audio/synthetis.py
tinyml4all/audio/classification/ClassificationAlbum.py
tinyml4all/audio/classification/OverlapPlot.py
tinyml4all/audio/classification/SequentialPlot.py
tinyml4all/audio/classification/__init__.py
tinyml4all/datasets/Iris.py
tinyml4all/datasets/Pets.py
tinyml4all/datasets/__init__.py
tinyml4all/image/HTTPD.py
tinyml4all/image/__init__.py
tinyml4all/image/capture.py
tinyml4all/image/debug.py
tinyml4all/support/Chartjs.py
tinyml4all/support/ChartjsCollection.py
tinyml4all/support/__init__.py
tinyml4all/support/capture.py
tinyml4all/support/colors.py
tinyml4all/support/override_help.py
tinyml4all/support/types.py
tinyml4all/support/userwarn.py
tinyml4all/support/capture/Counter.py
tinyml4all/support/capture/Progress.py
tinyml4all/support/capture/SerialReader.py
tinyml4all/support/capture/Timeout.py
tinyml4all/support/capture/__init__.py
tinyml4all/support/traits/HasClassmap.py
tinyml4all/support/traits/HasSources.py
tinyml4all/support/traits/IsPickleable.py
tinyml4all/support/traits/RequiresColumnsToBeConfigured.py
tinyml4all/support/traits/__init__.py
tinyml4all/tabular/Chain.py
tinyml4all/tabular/ProcessingBlock.py
tinyml4all/tabular/__init__.py
tinyml4all/tabular/capture.py
tinyml4all/tabular/classification/ClassificationChain.py
tinyml4all/tabular/classification/ClassificationTable.py
tinyml4all/tabular/classification/Pairplot.py
tinyml4all/tabular/classification/Scatter.py
tinyml4all/tabular/classification/__init__.py
tinyml4all/tabular/classification/models/DecisionTree.py
tinyml4all/tabular/classification/models/Estimator.py
tinyml4all/tabular/classification/models/RandomForest.py
tinyml4all/tabular/classification/models/__init__.py
tinyml4all/tabular/common/Source.py
tinyml4all/tabular/common/Table.py
tinyml4all/tabular/common/Targets.py
tinyml4all-1.0.9.dist-info/licenses/LICENSE
tinyml4all-1.0.9.dist-info/WHEEL
tinyml4all-1.0.9.dist-info/METADATA
tinyml4all-1.0.9.dist-info/RECORD
