Metadata-Version: 2.4
Name: tinyml4all
Version: 1.0.9
Summary: Train Machine Learning pipelines in Python, run on any embedded device
Author-email: Simone Salerno <info@salernosimone.com>
License-Expression: GPL-3.0-or-later
License-File: LICENSE
Requires-Dist: cached-property
Requires-Dist: contourpy
Requires-Dist: cycler
Requires-Dist: deprecation
Requires-Dist: durations
Requires-Dist: fonttools
Requires-Dist: hexdump
Requires-Dist: jinja2
Requires-Dist: jinja2-workarounds
Requires-Dist: joblib
Requires-Dist: kiwisolver
Requires-Dist: markupsafe
Requires-Dist: matplotlib
Requires-Dist: mpmath
Requires-Dist: numpy
Requires-Dist: packaging
Requires-Dist: pandas
Requires-Dist: pillow
Requires-Dist: prettytable
Requires-Dist: pyparsing
Requires-Dist: pyserial
Requires-Dist: python-dateutil
Requires-Dist: python-ulid
Requires-Dist: pytz
Requires-Dist: scikit-learn
Requires-Dist: scipy
Requires-Dist: seaborn
Requires-Dist: six
Requires-Dist: sympy
Requires-Dist: threadpoolctl
Requires-Dist: tqdm
Requires-Dist: tzdata
Requires-Dist: wcwidth
Requires-Dist: azure-cognitiveservices-speech
Requires-Dist: PyQt5
Requires-Dist: tensorflow==2.15.1 ; extra == "tensorflow"
Project-URL: Github, https://github.com/salernosimone/tinyml4all-python
Project-URL: Home, https://salernosimone.com/tinyml4all
Provides-Extra: tensorflow
